rjwt/__init__.py
rjwt/actor.py
rjwt/token.py
rjwt/tests/__init__.py
rjwt/tests/__main__.py
rjwt/tests/test_actor.py
rjwt-0.1.1.dist-info/METADATA
rjwt-0.1.1.dist-info/WHEEL
rjwt-0.1.1.dist-info/top_level.txt
rjwt-0.1.1.dist-info/RECORD
